zest.ploneglossaryhighlight-2.0.0-py2.7-nspkg.pth
zest/ploneglossaryhighlight/__init__.py
zest/ploneglossaryhighlight/adapters.py
zest/ploneglossaryhighlight/at.py
zest/ploneglossaryhighlight/configure.zcml
zest/ploneglossaryhighlight/dx.py
zest/ploneglossaryhighlight/interfaces.py
zest/ploneglossaryhighlight/rebuild_i18n.sh
zest/ploneglossaryhighlight/testing.py
zest/ploneglossaryhighlight/locales/zest.ploneglossaryhighlight.pot
zest/ploneglossaryhighlight/locales/nl/LC_MESSAGES/zest.ploneglossaryhighlight.mo
zest/ploneglossaryhighlight/locales/nl/LC_MESSAGES/zest.ploneglossaryhighlight.po
zest/ploneglossaryhighlight/profiles/default/browserlayer.xml
zest/ploneglossaryhighlight/profiles/default/metadata.xml
zest/ploneglossaryhighlight/tests/__init__.py
zest/ploneglossaryhighlight/tests/test_archetypes.py
zest/ploneglossaryhighlight/tests/test_dx.py
zest.ploneglossaryhighlight-2.0.0.dist-info/METADATA
zest.ploneglossaryhighlight-2.0.0.dist-info/WHEEL
zest.ploneglossaryhighlight-2.0.0.dist-info/entry_points.txt
zest.ploneglossaryhighlight-2.0.0.dist-info/namespace_packages.txt
zest.ploneglossaryhighlight-2.0.0.dist-info/top_level.txt
zest.ploneglossaryhighlight-2.0.0.dist-info/RECORD
