Metadata-Version: 2.1
Name: zest.ploneglossaryhighlight
Version: 2.0.0
Summary: Make highlighting PloneGlossary terms optional per page or folder.
Home-page: https://github.com/zestsoftware/zest.ploneglossaryhighlight
Author: Maurits van Rees
Author-email: m.van.rees@zestsoftware.nl
License: GPL
Keywords: plone glossary highlight
Platform: UNKNOWN
Classifier: Framework :: Plone
Classifier: Framework :: Plone :: 4.3
Classifier: License :: OSI Approved :: GNU General Public License (GPL)
Classifier: Programming Language :: Python
Classifier: Programming Language :: Python :: 2
Classifier: Programming Language :: Python :: 2.7
Requires-Dist: setuptools
Requires-Dist: Products.CMFPlone
Requires-Dist: Products.PloneGlossary (>=1.5.0)
Provides-Extra: archetypes
Requires-Dist: archetypes.schemaextender ; extra == 'archetypes'
Provides-Extra: dexterity
Requires-Dist: plone.behavior ; extra == 'dexterity'
Requires-Dist: plone.dexterity ; extra == 'dexterity'
Provides-Extra: test
Requires-Dist: plone.app.testing ; extra == 'test'
